Metadata-Version: 1.0
Name: request-rotate
Version: 1.0
Summary: Scrape and test proxies until one works. requests adapter
Home-page: https://github.com/9sv/request-rotate
Author: Surtains
Author-email: surtains@riseup.net
License: UNKNOWN
Platform: UNKNOWN
